<?xml version="1.0" ?>
<PiavcaMotions>
	<SubMotion End="3.90000009537" Name="postures_split_0" Start="2.60833334923">
		<Motion name="postures"/>
	</SubMotion>
	<SubMotion End="6.00833320618" Name="postures_split_1" Start="4.44166660309">
		<Motion name="postures"/>
	</SubMotion>
	<SubMotion End="26.3333339691" Name="postures_split_2" Start="24.1000003815">
		<Motion name="postures"/>
	</SubMotion>
	<SubMotion End="51.1666679382" Name="postures_split_3" Start="49.0999984741">
		<Motion name="postures"/>
	</SubMotion>
</PiavcaMotions>
